{
  "type": "botanypots:crop",
  "seed": {
    "item": "techreborn:tin_ore"
  },
  "categories": [
    "oreT2",
    "oreT3",
    "oreT4"
  ],
  "growthTicks": 1200,
  "display": {
    "type": "botanypots:aging",
    "block": "techreborn:tin_ore"
  },
  "drops": [
    {
      "chance": 1.00,
      "output": {
        "item": "techreborn:raw_tin"
      },
      "minRolls": 1,
      "maxRolls": 2
    },
    {
      "chance": 0.15,
      "output": {
        "item": "techreborn:raw_tin"
      },
      "minRolls": 1,
      "maxRolls": 2
    }
  ]
}